flask_ldp.py
Flask_LDP-0.1.1.dist-info/WHEEL
Flask_LDP-0.1.1.dist-info/METADATA
Flask_LDP-0.1.1.dist-info/RECORD
