Metadata-Version: 2.1
Name: Flask-LDP
Version: 0.1.1
Summary: Configure LDP logging handlers and middleware for your Flask app.
Home-page: https://github.com/alkivi-sas/flask-ldp
Author: Alkivi
Author-email: anthony@alkivi.fr
Maintainer: Anthony Martinet
Maintainer-email: anthony@alkivi.fr
Requires-Python: >=3.5
Classifier: Environment :: Web Environment
Classifier: Intended Audience :: Developers
Classifier: License :: OSI Approved :: MIT License
Classifier: Operating System :: OS Independent
Classifier: Programming Language :: Python
Classifier: Topic :: Software Development :: Libraries :: Python Modules
Requires-Dist: Flask
Requires-Dist: logging-ldp
